{
  "unpublishedPage": {
    "name": "Page3",
    "slug": "page3",
    "layouts": [
      {
        "viewMode": false,
        "dsl": {
          "widgetName": "MainContainer",
          "backgroundColor": "none",
          "rightColumn": 1224.0,
          "snapColumns": 64.0,
          "detachFromLayout": true,
          "widgetId": "0",
          "topRow": 0.0,
          "bottomRow": 700.0,
          "containerStyle": "none",
          "snapRows": 70.0,
          "parentRowSpace": 1.0,
          "type": "CANVAS_WIDGET",
          "canExtend": true,
          "version": 45.0,
          "minHeight": 710.0,
          "parentColumnSpace": 1.0,
          "dynamicBindingPathList": [],
          "leftColumn": 0.0,
          "children": []
        },
        "layoutOnLoadActions": [],
        "validOnPageLoadActions": true,
        "id": "6196063d9198ee6c885e68c0",
        "deleted": false,
        "policies": [],
        "userPermissions": []
      }
    ],
    "userPermissions": [],
    "policies": []
  },
  "publishedPage": {
    "name": "Page3",
    "slug": "page3",
    "layouts": [
      {
        "viewMode": false,
        "dsl": {
          "widgetName": "MainContainer",
          "backgroundColor": "none",
          "rightColumn": 1224.0,
          "snapColumns": 64.0,
          "detachFromLayout": true,
          "widgetId": "0",
          "topRow": 0.0,
          "bottomRow": 700.0,
          "containerStyle": "none",
          "snapRows": 70.0,
          "parentRowSpace": 1.0,
          "type": "CANVAS_WIDGET",
          "canExtend": true,
          "version": 45.0,
          "minHeight": 710.0,
          "parentColumnSpace": 1.0,
          "dynamicBindingPathList": [],
          "leftColumn": 0.0,
          "children": []
        },
        "layoutOnLoadActions": [],
        "validOnPageLoadActions": true,
        "id": "6196063d9198ee6c885e68c0",
        "deleted": false,
        "policies": [],
        "userPermissions": []
      }
    ],
    "userPermissions": [],
    "policies": []
  },
  "deleted": false,
  "policies": [],
  "userPermissions": [
    "read:pages",
    "manage:pages"
  ],
  "gitSyncId": "61960188be1a830eec0e2cf2_619602f3be1a830eec0e2d01"
}